brewbar/__init__.py
brewbar/core.py
brewbar-1.2.2.dist-info/METADATA
brewbar-1.2.2.dist-info/WHEEL
brewbar-1.2.2.dist-info/licenses/LICENSE
brewbar-1.2.2.dist-info/RECORD
