Metadata-Version: 2.4
Name: brewbar
Version: 1.2.2
Summary: A progress bar for Python that brews beer while your code runs
Project-URL: Homepage, https://github.com/Harish-SN/brewbar
Project-URL: Repository, https://github.com/Harish-SN/brewbar
Project-URL: Issues, https://github.com/Harish-SN/brewbar/issues
Author-email: Harish <snharish85@gmail.com>
License: MIT
License-File: LICENSE
Keywords: beer,fun,progress,progress-bar,terminal
Classifier: Development Status :: 5 - Production/Stable
Classifier: Intended Audience :: Developers
Classifier: License :: OSI Approved :: MIT License
Classifier: Programming Language :: Python :: 3
Classifier: Programming Language :: Python :: 3.8
Classifier: Programming Language :: Python :: 3.9
Classifier: Programming Language :: Python :: 3.10
Classifier: Programming Language :: Python :: 3.11
Classifier: Programming Language :: Python :: 3.12
Classifier: Topic :: Software Development :: Libraries :: Python Modules
Classifier: Topic :: System :: Shells
Classifier: Topic :: Terminals
Requires-Python: >=3.8
